streamlit_render/__init__.py
streamlit_render/version.py
streamlit_render/core/__init__.py
streamlit_render/core/callback.py
streamlit_render/core/element.py
streamlit_render/core/exceptions.py
streamlit_render/core/frame.py
streamlit_render/core/render.py
streamlit_render/frontend/build/404.html
streamlit_render/frontend/build/camera.gltf
streamlit_render/frontend/build/index.html
streamlit_render/frontend/build/_next/static/chunks/1023.6826e7979a3e09f8.js
streamlit_render/frontend/build/_next/static/chunks/103.250d6c6a4b888906.js
streamlit_render/frontend/build/_next/static/chunks/1034.e0a5fa6e49fe02dd.js
streamlit_render/frontend/build/_next/static/chunks/1041.32c6ad63922d7b94.js
streamlit_render/frontend/build/_next/static/chunks/1109.d3a6e48b4b4d97dd.js
streamlit_render/frontend/build/_next/static/chunks/1121.a68a6a9e1a36c7cc.js
streamlit_render/frontend/build/_next/static/chunks/1157.c14db5220094bced.js
streamlit_render/frontend/build/_next/static/chunks/1197.30c56ec8be9d1429.js
streamlit_render/frontend/build/_next/static/chunks/1261.4407e2d87b2d2c93.js
streamlit_render/frontend/build/_next/static/chunks/1347.1f3b6d64496c2e26.js
streamlit_render/frontend/build/_next/static/chunks/137.a24ab467fa41ea7e.js
streamlit_render/frontend/build/_next/static/chunks/1379.01afe32e71a8db40.js
streamlit_render/frontend/build/_next/static/chunks/1397.5e6133806543712d.js
streamlit_render/frontend/build/_next/static/chunks/1404.ae0d7b7f8752e6ff.js
streamlit_render/frontend/build/_next/static/chunks/1477.1c15463c2ff0ede7.js
streamlit_render/frontend/build/_next/static/chunks/150.b4eedb1a1bdf80b5.js
streamlit_render/frontend/build/_next/static/chunks/1605.41b1a120371aa9b9.js
streamlit_render/frontend/build/_next/static/chunks/1624.ae901bc536e03b6f.js
streamlit_render/frontend/build/_next/static/chunks/1634.bef7ecc0855e747b.js
streamlit_render/frontend/build/_next/static/chunks/1691.261389f5db962750.js
streamlit_render/frontend/build/_next/static/chunks/1751.301e1cfaf81ca4f9.js
streamlit_render-1.0.1.dist-info/LICENSE
streamlit_render-1.0.1.dist-info/METADATA
streamlit_render-1.0.1.dist-info/WHEEL
streamlit_render-1.0.1.dist-info/top_level.txt
streamlit_render-1.0.1.dist-info/RECORD
