Metadata-Version: 2.1
Name: streamlit-render
Version: 1.0.1
Summary: React Components for Streamlit.
Home-page: https://www.facebook.com/blong1204
Author: baolongdev
License: MIT
Requires-Python: >=3.6
License-File: LICENSE
Requires-Dist: streamlit (>=1.4.0)
